{
    "source": "CONVERSE.B",
    "index": 94,
    "id": 193,
    "name": [
        "Compassion"
    ],
    "description": [
        "the altar of Compassion.",
        "F3"
    ],
    "conversation": {
        "39": [
            "WAIT",
            "\nAs you kneel before the altar, a mystical voice sounds in your head.",
            "WAIT",
            "\n\n",
            [
                "IF",
                [
                    20,
                    178,
                    211,
                    40,
                    131
                ],
                [
                    "\"Thou hast much to learn about compassion.\"",
                    [
                        "JUMP",
                        260
                    ]
                ],
                []
            ],
            [
                "IF",
                [
                    20,
                    178,
                    211,
                    80,
                    131
                ],
                [
                    "\"Thy deeds have shown admirable compassion.\""
                ],
                [
                    "\"Thy deeds serve as an example to all.\""
                ]
            ],
            "WAIT",
            "\n\nDo you wish to meditate at this altar? ",
            [
                "ASKC",
                "yn"
            ],
            [
                "KEYWORDS",
                "n",
                [
                    "BYE"
                ]
            ],
            [
                "IF",
                [
                    23,
                    178,
                    211,
                    0,
                    134
                ],
                [
                    [
                        "DECL",
                        [
                            0,
                            178,
                            168,
                            211,
                            0
                        ]
                    ],
                    [
                        "JUMP",
                        449
                    ]
                ],
                []
            ],
            [
                "DECL",
                [
                    0,
                    178,
                    168,
                    211,
                    0
                ]
            ],
            [
                "DECL",
                [
                    2,
                    178,
                    168,
                    211,
                    1
                ]
            ],
            "\n",
            [
                "SETNAME",
                [
                    0,
                    178,
                    211,
                    0,
                    221
                ]
            ],
            "#2. $Y\n",
            [
                "DECL",
                [
                    0,
                    178,
                    168,
                    0,
                    178,
                    211,
                    1,
                    144
                ]
            ],
            [
                "DECL",
                [
                    2,
                    178,
                    168,
                    2,
                    178,
                    211,
                    1,
                    144
                ]
            ],
            [
                "IF",
                [
                    0,
                    178,
                    23,
                    178,
                    132
                ],
                [
                    [
                        "JUMP",
                        345
                    ]
                ],
                []
            ],
            "\"Who will meditate?\" ",
            [
                "INPUTNUM",
                0
            ],
            [
                "IF",
                [
                    0,
                    178,
                    211,
                    0,
                    134
                ],
                [
                    "\n",
                    "BYE"
                ],
                []
            ],
            [
                "DECL",
                [
                    0,
                    178,
                    168,
                    0,
                    178,
                    211,
                    1,
                    145
                ]
            ],
            [
                "IF",
                [
                    0,
                    178,
                    23,
                    178,
                    129
                ],
                [
                    [
                        "JUMP",
                        330
                    ]
                ],
                []
            ],
            "\"Speak the Mantra of Compassion.\"\n",
            "ASK",
            "\n\"$Z... $Z...\"",
            "WAIT",
            "\n\n\"$Z... $Z...\"",
            "WAIT",
            "\n\n\"$Z... $Z...\"",
            "WAIT",
            "\n",
            [
                "KEYWORDS",
                "mu",
                [
                    "\"No beast so fierce but shows some touch of pity.\"",
                    "WAIT",
                    "\n\n\"Sweet mercy is nobility's true badge.\"",
                    "WAIT",
                    [
                        "JUMP",
                        673
                    ]
                ]
            ],
            [
                "KEYWORDS",
                "*",
                [
                    "You receive no enlightenment.",
                    "WAIT",
                    [
                        "JUMP",
                        914
                    ]
                ]
            ]
        ],
        "673": [
            [
                "IF",
                [
                    211,
                    235,
                    0,
                    171,
                    211,
                    0,
                    134
                ],
                [
                    [
                        "ADD_KARMA",
                        [
                            211,
                            10
                        ]
                    ],
                    [
                        "SETF",
                        [
                            211,
                            235
                        ],
                        [
                            0
                        ]
                    ]
                ],
                []
            ],
            [
                "IF",
                [
                    211,
                    192,
                    0,
                    171,
                    211,
                    193,
                    0,
                    171,
                    149,
                    211,
                    194,
                    0,
                    171,
                    149,
                    211,
                    195,
                    0,
                    171,
                    149,
                    211,
                    196,
                    0,
                    171,
                    149,
                    211,
                    197,
                    0,
                    171,
                    149,
                    211,
                    198,
                    0,
                    171,
                    149,
                    211,
                    199,
                    0,
                    171,
                    149
                ],
                [
                    [
                        "CLEARF",
                        [
                            211,
                            192
                        ],
                        [
                            0
                        ]
                    ],
                    [
                        "CLEARF",
                        [
                            211,
                            193
                        ],
                        [
                            0
                        ]
                    ],
                    [
                        "CLEARF",
                        [
                            211,
                            194
                        ],
                        [
                            0
                        ]
                    ],
                    [
                        "CLEARF",
                        [
                            211,
                            195
                        ],
                        [
                            0
                        ]
                    ],
                    [
                        "CLEARF",
                        [
                            211,
                            196
                        ],
                        [
                            0
                        ]
                    ],
                    [
                        "CLEARF",
                        [
                            211,
                            197
                        ],
                        [
                            0
                        ]
                    ],
                    [
                        "CLEARF",
                        [
                            211,
                            198
                        ],
                        [
                            0
                        ]
                    ],
                    [
                        "CLEARF",
                        [
                            211,
                            199
                        ],
                        [
                            0
                        ]
                    ],
                    [
                        "SETF",
                        [
                            211,
                            235
                        ],
                        [
                            0
                        ]
                    ]
                ],
                []
            ],
            [
                "DECL",
                [
                    1,
                    178,
                    168,
                    0,
                    178,
                    211,
                    0,
                    221
                ]
            ],
            [
                "DECL",
                [
                    2,
                    178,
                    168,
                    1,
                    178,
                    211,
                    0,
                    225
                ]
            ],
            [
                "IF",
                [
                    2,
                    178,
                    211,
                    7,
                    129
                ],
                [
                    [
                        "JUMP",
                        914
                    ]
                ],
                []
            ],
            [
                "DECL",
                [
                    3,
                    178,
                    168,
                    1,
                    178,
                    211,
                    0,
                    224
                ]
            ],
            [
                "IF",
                [
                    3,
                    178,
                    210,
                    255,
                    3,
                    0,
                    0,
                    2,
                    178,
                    180,
                    130
                ],
                [
                    [
                        "DECL",
                        [
                            2,
                            178,
                            168,
                            1,
                            178,
                            211,
                            1,
                            225
                        ]
                    ],
                    [
                        "DECL",
                        [
                            4,
                            178,
                            168,
                            1,
                            178,
                            211,
                            3,
                            228
                        ]
                    ],
                    [
                        "SETNAME",
                        [
                            1,
                            178
                        ]
                    ],
                    "\n\n$Y has gained a level...",
                    "WAIT",
                    "\n\nand dexterity!",
                    "WAIT"
                ],
                []
            ],
            "\n\n\"There is naught else for you to learn here and now.\"",
            "WAIT",
            "\n\n\"Return when thy journey has progressed further.\"\n",
            "BYE"
        ]
    }
}